{
    "title": "vie associative",
    "url": "https://www.polytech.sorbonne-universite.fr/vie-associative",
    "content": "Les associations et clubs affiliés au BDE (Bureau Des Etudiants) de Polytech Sorbonne sont nombreux et variés. Vous trouverez leurs actualités en détail sur leurs pages/réseaux sociaux respectifs.",
    "category1": "polytech.sorbonne-universite.fr",
    "category2": "l'école",
    "category3": "vie à l'école",
    "category4": "vie associative",
    "filierespecifique": "NA",
    "datespecifique": "NA"
}